<?xml version="1.0" encoding="utf-8" ?>
<dwsync>
<file name="ig01_100-100.jpg" server="ftp.tellybear.co" local="130388897140000000" remote="130388810400000000" />
<file name="ig02_100-100.jpg" server="ftp.tellybear.co" local="130388897740000000" remote="130388810400000000" />
<file name="ig03_100-100.jpg" server="ftp.tellybear.co" local="130388897820000000" remote="130388810400000000" />
<file name="ig04_70-70.jpg" server="ftp.tellybear.co" local="130388931940000000" remote="130388810400000000" />
<file name="ig05_70-70.jpg" server="ftp.tellybear.co" local="130388932040000000" remote="130388810400000000" />
<file name="ig06_70-70.jpg" server="ftp.tellybear.co" local="130388932140000000" remote="130388810400000000" />
<file name="ig07_70-70.jpg" server="ftp.tellybear.co" local="130388932260000000" remote="130388811000000000" />
<file name="ig08_215-80.jpg" server="ftp.tellybear.co" local="130388937220000000" remote="130388811000000000" />
</dwsync>